jet_jammer.py
jet_jammer-0.3.3.dist-info/LICENSE
jet_jammer-0.3.3.dist-info/WHEEL
jet_jammer-0.3.3.dist-info/METADATA
jet_jammer-0.3.3.dist-info/RECORD
