Metadata-Version: 2.1
Name: jet-jammer
Version: 0.3.3
Summary: Jamming tool
Author: Jack Reilly
Author-email: jackdreilly@gmail.com
Requires-Python: >=3.9,<4.0
Classifier: Programming Language :: Python :: 3
Classifier: Programming Language :: Python :: 3.10
Classifier: Programming Language :: Python :: 3.9
Requires-Dist: MIDIUtil (>=1.2.1,<2.0.0)
Requires-Dist: fastapi (>=0.70.0,<0.71.0)
Requires-Dist: platformdirs (>=2.4.0,<3.0.0)
Requires-Dist: pydantic (>=1.8.2,<2.0.0)
Requires-Dist: uvicorn (>=0.15.0,<0.16.0)
